{
  "decisions": [
    {
      "decision": "pass",
      "family_id": "qf_flash_corr_vs_coint_01",
      "practice_target": "区分相关性与协整在定义和时间范围上的差异",
      "reason": "该闪卡家族直接训练相关性与协整的核心区别，包括定义和时间维度，属于当前step的可学习内容。"
    },
    {
      "decision": "pass",
      "family_id": "qf_long_corr_vs_coint_01",
      "practice_target": "阐述相关性与协整的区别并说明协整在配对交易中的重要性",
      "reason": "该长文家族要求学生解释相关性与协整的区别及其在配对交易中的应用，训练的是当前step的核心概念和实际应用能力。"
    },
    {
      "decision": "pass",
      "family_id": "qf_quiz_corr_vs_coint_01",
      "practice_target": "辨析相关性与协整的本质区别及其在分散投资和配对交易中的应用",
      "reason": "该测验家族通过选择题辨析相关性与协整的定义、时间范围和应用场景，直接对应当前step的学习目标。"
    }
  ],
  "gate": "question_bank_gate",
  "kept_family_ids": [
    "qf_flash_corr_vs_coint_01",
    "qf_quiz_corr_vs_coint_01",
    "qf_long_corr_vs_coint_01"
  ],
  "rejected_families": {
    "flashcard_families": [],
    "longform_families": [],
    "quiz_families": []
  },
  "rejected_family_ids": [],
  "summary": {
    "failed": 0,
    "passed": 3,
    "uncertain": 0
  }
}
